{
  "_buildCommand2" : {
    "command" : "build",
    "skipDependencies" : false,
    "style" : "buildAndRun"
  },
  "buildCommand" : "build",
  "configuredTargets" : [
    {
      "guid" : "6b3213f9c463fa74d1139a938267e79f7ec2b6f50b44cdaa3018e31be3a0d31e"
    }
  ],
  "containerPath" : "/Users/dnamala/Downloads/MoviesApp/MoviesApp.xcodeproj",
  "continueBuildingAfterErrors" : false,
  "enableIndexBuildArena" : false,
  "hideShellScriptEnvironment" : false,
  "parameters" : {
    "action" : "build",
    "overrides" : {
      "commandLine" : {
        "table" : {
          "CODE_SIGN_IDENTITY" : "",
          "CODE_SIGNING_ALLOWED" : "NO",
          "CODE_SIGNING_REQUIRED" : "NO"
        }
      },
      "synthesized" : {
        "table" : {
          "ACTION" : "build",
          "ENABLE_PREVIEWS" : "NO"
        }
      }
    }
  },
  "schemeCommand" : "launch",
  "shouldCollectMetrics" : false,
  "showNonLoggedProgress" : true,
  "useDryRun" : false,
  "useImplicitDependencies" : false,
  "useLegacyBuildLocations" : false,
  "useParallelTargets" : true
}